insipid_sphinx_theme/__init__.py
insipid_sphinx_theme/insipid/copyright.html
insipid_sphinx_theme/insipid/ethical-ad.html
insipid_sphinx_theme/insipid/footer.html
insipid_sphinx_theme/insipid/fullscreen-button.html
insipid_sphinx_theme/insipid/home.html
insipid_sphinx_theme/insipid/indices.html
insipid_sphinx_theme/insipid/last-updated.html
insipid_sphinx_theme/insipid/layout.html
insipid_sphinx_theme/insipid/page.html
insipid_sphinx_theme/insipid/pdf-button.html
insipid_sphinx_theme/insipid/repo-button.html
insipid_sphinx_theme/insipid/search-button.html
insipid_sphinx_theme/insipid/separator.html
insipid_sphinx_theme/insipid/show-source.html
insipid_sphinx_theme/insipid/sidebar-button.html
insipid_sphinx_theme/insipid/sphinx.html
insipid_sphinx_theme/insipid/theme.conf
insipid_sphinx_theme/insipid/static/insipid-sidebar-readthedocs.css_t
insipid_sphinx_theme/insipid/static/insipid-sidebar.js_t
insipid_sphinx_theme/insipid/static/insipid.css_t
insipid_sphinx_theme/insipid/static/insipid.js
insipid_sphinx_theme-0.4.3.dist-info/licenses/LICENSE
insipid_sphinx_theme-0.4.3.dist-info/METADATA
insipid_sphinx_theme-0.4.3.dist-info/WHEEL
insipid_sphinx_theme-0.4.3.dist-info/entry_points.txt
insipid_sphinx_theme-0.4.3.dist-info/top_level.txt
insipid_sphinx_theme-0.4.3.dist-info/RECORD
